gitmine/__init__.py
gitmine/constants.py
gitmine/endpoints.py
gitmine/gitmine.py
gitmine/paths.py
gitmine/utils.py
gitmine/commands/__init__.py
gitmine/commands/config.py
gitmine/commands/get.py
gitmine/commands/go.py
gitmine/models/__init__.py
gitmine/models/github_elements.py
gitmine/version/__init__.py
gitmine-0.0.11.dist-info/LICENSE
gitmine-0.0.11.dist-info/METADATA
gitmine-0.0.11.dist-info/WHEEL
gitmine-0.0.11.dist-info/entry_points.txt
gitmine-0.0.11.dist-info/top_level.txt
gitmine-0.0.11.dist-info/RECORD
