Metadata-Version: 2.1
Name: gitmine
Version: 0.0.11
Summary: Simple command-line app for querying assigned Issues and PRs from Github.
Home-page: https://github.com/joecummings/gitmine
Author: Joe Cummings, Alexis Baudron
Author-email: jrcummings27@gmail.com
License: MIT
Platform: UNKNOWN
Requires-Python: >=3.6
Requires-Dist: PyYAML (==5.4)
Requires-Dist: click (==7.1.2)
Requires-Dist: colorama (==0.4.3)
Requires-Dist: furl (==2.1.2)
Requires-Dist: requests (==2.24.0)
Requires-Dist: tabulate (==0.8.9)
